foillib/__about__.py
foillib/__init__.py
foillib/_common.py
foillib/_naca4.py
foillib/_naca5.py
foillib/_naca_common.py
foillib/_types.py
foillib/bezier.py
foillib/naca.py
foillib-0.0.1.dist-info/LICENSE
foillib-0.0.1.dist-info/METADATA
foillib-0.0.1.dist-info/WHEEL
foillib-0.0.1.dist-info/top_level.txt
foillib-0.0.1.dist-info/RECORD
