Metadata-Version: 2.1
Name: foillib
Version: 0.0.1
Summary: A small utility for generating airfoils
Author-email: "Nathan A. Rooy" <nathanrooy@gmail.com>
License: GNU GENERAL PUBLIC LICENSE
Project-URL: Code, https://github.com/nathanrooy/foillib
Project-URL: Issues, https://github.com/nathanrooy/foillib/issues
Keywords: aerodynamics,airfoil,naca,bezier,parametric
Classifier: Development Status :: 4 - Beta
Classifier: Intended Audience :: Science/Research
Classifier: License :: OSI Approved :: MIT License
Classifier: Operating System :: OS Independent
Classifier: Programming Language :: Python
Classifier: Programming Language :: Python :: 3
Classifier: Programming Language :: Python :: 3.7
Classifier: Programming Language :: Python :: 3.8
Classifier: Programming Language :: Python :: 3.9
Classifier: Programming Language :: Python :: 3.10
Classifier: Programming Language :: Python :: 3.11
Classifier: Topic :: Utilities
Requires-Python: >=3.7
License-File: LICENSE
